apitestbasic/GraphqlApi/__init__.py
apitestbasic/GraphqlApi/gen_params.py
apitestbasic/GraphqlApi/graphql_api.py
apitestbasic/GraphqlApi/special_graphql_api.py
apitestbasic/GraphqlApi/tools.py
apitestbasic/User/__init__.py
apitestbasic/User/base_user.py
apitestbasic/__init__.py
apitestbasic/graphql_api_codegen.py
apitestbasic-2.0.0.dist-info/WHEEL
apitestbasic-2.0.0.dist-info/METADATA
apitestbasic-2.0.0.dist-info/RECORD
