Metadata-Version: 2.1
Name: apitestbasic
Version: 2.0.0
Summary: 
Author: lin
Requires-Python: >=3.9,<4.0
Classifier: Programming Language :: Python :: 3
Classifier: Programming Language :: Python :: 3.9
Requires-Dist: PyHamcrest (>=2.0.2,<3.0.0)
Requires-Dist: jmespath (>=0.10.0,<0.11.0)
Requires-Dist: pytest (>=6.2.4,<7.0.0)
Requires-Dist: python-utils (>=2.5.6,<3.0.0)
Requires-Dist: sgqlc (>=13.0,<14.0)
